CreateCloudMap-0.9.2.dist-info/DESCRIPTION.rst
CreateCloudMap-0.9.2.dist-info/METADATA
CreateCloudMap-0.9.2.dist-info/RECORD
CreateCloudMap-0.9.2.dist-info/WHEEL
CreateCloudMap-0.9.2.dist-info/entry_points.txt
CreateCloudMap-0.9.2.dist-info/metadata.json
CreateCloudMap-0.9.2.dist-info/top_level.txt
cloudmap/__init__.py
cloudmap/_version.py
cloudmap/create_map.py
cloudmap/dundee.py
cloudmap/geo.py
cloudmap/geo_dundee.py
cloudmap/geo_jma.py
cloudmap/mkdir.py
cloudmap/polar.py
cloudmap/satellite.py
cloudmap/satellites.py
