Metadata-Version: 2.0
Name: CreateCloudMap
Version: 0.9.2
Summary: Create a cloud map for xplanet using satellite images from the Dundee Satellite Receiving Station
Home-page: https://github.com/jmozmoz/cloudmap
Author: Joachim Herb
Author-email: Joachim.Herb@gmx.de
License: GPL3
Platform: UNKNOWN
Classifier: Programming Language :: Python
Classifier: Programming Language :: Python :: 2
Classifier: Programming Language :: Python :: 2.7
Classifier: Programming Language :: Python :: 3
Classifier: Programming Language :: Python :: 3.3
Classifier: Programming Language :: Python :: 3.4
Classifier: Programming Language :: Python :: 3.5
Classifier: Programming Language :: Python :: 3.6
Classifier: License :: OSI Approved :: GNU General Public License v3 (GPLv3)
Classifier: Operating System :: OS Independent
Classifier: Development Status :: 4 - Beta
Classifier: Environment :: Console
Classifier: Intended Audience :: End Users/Desktop
Classifier: Topic :: Desktop Environment
Classifier: Topic :: Multimedia :: Graphics
Classifier: Topic :: Scientific/Engineering :: Atmospheric Science
Classifier: Topic :: Scientific/Engineering :: GIS
Classifier: Topic :: Scientific/Engineering :: Visualization
Classifier: Topic :: Utilities
Requires-Dist: configparser (>=3.5.0b1)
Requires-Dist: datetime
Requires-Dist: numpy
Requires-Dist: pillow (>=3.0.0)
Requires-Dist: pyresample
Requires-Dist: requests
Requires-Dist: scipy
Requires-Dist: setuptools (>=0.7.2)
Provides-Extra: cartopy
Requires-Dist: cartopy; extra == 'cartopy'
Requires-Dist: pyshp; extra == 'cartopy'
Requires-Dist: shapely; extra == 'cartopy'
Provides-Extra: debug_cartopy
Requires-Dist: cartopy; extra == 'debug_cartopy'
Requires-Dist: matplotlib; extra == 'debug_cartopy'
Requires-Dist: pyshp; extra == 'debug_cartopy'
Requires-Dist: shapely; extra == 'debug_cartopy'
Provides-Extra: debug_pyresample
Requires-Dist: basemap; extra == 'debug_pyresample'
Requires-Dist: matplotlib; extra == 'debug_pyresample'
